pystride-0.1.2.dist-info/DESCRIPTION.rst
pystride-0.1.2.dist-info/METADATA
pystride-0.1.2.dist-info/RECORD
pystride-0.1.2.dist-info/WHEEL
pystride-0.1.2.dist-info/metadata.json
pystride-0.1.2.dist-info/top_level.txt
stride/__init__.py
stride/stride.py
